odoo/addons/web_tree_dynamic_colored_field/README.rst
odoo/addons/web_tree_dynamic_colored_field/__init__.py
odoo/addons/web_tree_dynamic_colored_field/__manifest__.py
odoo/addons/web_tree_dynamic_colored_field/demo/res_users.xml
odoo/addons/web_tree_dynamic_colored_field/static/description/icon.png
odoo/addons/web_tree_dynamic_colored_field/static/src/js/web_tree_dynamic_colored_field.js
odoo/addons/web_tree_dynamic_colored_field/views/web_tree_dynamic_colored_field.xml
odoo11_addon_web_tree_dynamic_colored_field-11.0.1.0.1.dist-info/DESCRIPTION.rst
odoo11_addon_web_tree_dynamic_colored_field-11.0.1.0.1.dist-info/METADATA
odoo11_addon_web_tree_dynamic_colored_field-11.0.1.0.1.dist-info/RECORD
odoo11_addon_web_tree_dynamic_colored_field-11.0.1.0.1.dist-info/WHEEL
odoo11_addon_web_tree_dynamic_colored_field-11.0.1.0.1.dist-info/metadata.json
odoo11_addon_web_tree_dynamic_colored_field-11.0.1.0.1.dist-info/top_level.txt
