Metadata-Version: 2.0
Name: odoo11-addon-web-tree-dynamic-colored-field
Version: 11.0.1.0.1
Summary: Allows you to dynamically color fields on tree views
Home-page: https://github.com/OCA/web
Author: Camptocamp, Therp BV, Odoo Community Association (OCA)
Author-email: support@odoo-community.org
License: AGPL-3
Platform: UNKNOWN
Classifier: Programming Language :: Python
Classifier: Framework :: Odoo
Classifier: License :: OSI Approved :: GNU Affero General Public License v3
Requires-Python: >=2.7, !=3.0.*, !=3.1.*, !=3.2.*, !=3.3.*, !=3.4.*
Requires-Dist: odoo (<11.1dev,>=11.0a)
